lazywrapper/__init__.py
lazywrapper/lazywrap.py
lazywrapper-0.1.0b0.dist-info/licenses/LICENSE.md
lazywrapper-0.1.0b0.dist-info/METADATA
lazywrapper-0.1.0b0.dist-info/WHEEL
lazywrapper-0.1.0b0.dist-info/top_level.txt
lazywrapper-0.1.0b0.dist-info/RECORD
