Metadata-Version: 2.4
Name: lazywrapper
Version: 0.1.0b0
Summary: Wrapper for lazy functions / variables
Author-email: ttk-adm <218129711+ttk-adm@users.noreply.github.com>
License: MIT License
Project-URL: Homepage, https://github.com/ttk-adm/lazywrapper
Project-URL: Repository, https://github.com/ttk-adm/lazywrapper
Project-URL: Issues, https://github.com/ttk-adm/lazywrapper/issues
Classifier: Intended Audience :: Developers
Classifier: License :: OSI Approved :: MIT License
Classifier: Programming Language :: Python :: 3
Requires-Python: >=3.10
License-File: LICENSE.md
Provides-Extra: test
Requires-Dist: pytest; extra == "test"
Provides-Extra: dev
Requires-Dist: lazywrapper[test]; extra == "dev"
Requires-Dist: black; extra == "dev"
Requires-Dist: flake8; extra == "dev"
Requires-Dist: ruff; extra == "dev"
Provides-Extra: doc
Requires-Dist: lazywrapper[test]; extra == "doc"
Requires-Dist: sphinx; extra == "doc"
Requires-Dist: sphinx-autodoc-typehints; extra == "doc"
Requires-Dist: pydata-sphinx-theme; extra == "doc"
Dynamic: license-file
